glance_tempest_plugin/README.rst
glance_tempest_plugin/__init__.py
glance_tempest_plugin/config.py
glance_tempest_plugin/plugin.py
glance_tempest_plugin/services/__init__.py
glance_tempest_plugin/tests/__init__.py
glance_tempest_plugin/tests/api/__init__.py
glance_tempest_plugin/tests/rbac/__init__.py
glance_tempest_plugin/tests/rbac/v2/__init__.py
glance_tempest_plugin/tests/rbac/v2/base.py
glance_tempest_plugin/tests/rbac/v2/test_project_admin_tests.py
glance_tempest_plugin/tests/rbac/v2/test_project_members_tests.py
glance_tempest_plugin/tests/rbac/v2/test_project_reader_tests.py
glance_tempest_plugin/tests/rbac/v2/metadefs/__init__.py
glance_tempest_plugin/tests/rbac/v2/metadefs/test_namespaces.py
glance_tempest_plugin/tests/rbac/v2/metadefs/test_objects.py
glance_tempest_plugin/tests/rbac/v2/metadefs/test_properties.py
glance_tempest_plugin/tests/rbac/v2/metadefs/test_resource_types.py
glance_tempest_plugin/tests/rbac/v2/metadefs/test_tags.py
glance_tempest_plugin/tests/scenario/__init__.py
glance_tempest_plugin-0.14.0.dist-info/AUTHORS
glance_tempest_plugin-0.14.0.dist-info/LICENSE
glance_tempest_plugin-0.14.0.dist-info/METADATA
glance_tempest_plugin-0.14.0.dist-info/WHEEL
glance_tempest_plugin-0.14.0.dist-info/entry_points.txt
glance_tempest_plugin-0.14.0.dist-info/pbr.json
glance_tempest_plugin-0.14.0.dist-info/top_level.txt
glance_tempest_plugin-0.14.0.dist-info/RECORD
